README.rst
setup.cfg
setup.py
suap_xlutils.egg-info/PKG-INFO
suap_xlutils.egg-info/SOURCES.txt
suap_xlutils.egg-info/dependency_links.txt
suap_xlutils.egg-info/entry_points.txt
suap_xlutils.egg-info/not-zip-safe
suap_xlutils.egg-info/requires.txt
suap_xlutils.egg-info/top_level.txt
xlutils/__init__.py
xlutils/compat.py
xlutils/copy.py
xlutils/display.py
xlutils/filter.py
xlutils/license.txt
xlutils/margins.py
xlutils/save.py
xlutils/styles.py
xlutils/version.txt
xlutils/view.py
xlutils/tests/__init__.py
xlutils/tests/compat.py
xlutils/tests/date.xls
xlutils/tests/datetime.xls
xlutils/tests/fixtures.py
xlutils/tests/ragged.xls
xlutils/tests/sample.xlsx
xlutils/tests/test.xls
xlutils/tests/test_copy.py
xlutils/tests/test_docs.py
xlutils/tests/test_filter.py
xlutils/tests/test_save.py
xlutils/tests/test_styles.py
xlutils/tests/test_view.py
xlutils/tests/testall.xls
xlutils/tests/testnoformatting.xls