Metadata-Version: 2.1
Name: suap-xlutils
Version: 2.0.2
Summary: Utilities for working with Excel files that require both suap-xlrd and xlwt
Home-page: http://www.python-excel.org
Author: Chris Withers
Author-email: chris@simplistix.co.uk
License: MIT
Keywords: excel xls xlrd xlwt
Platform: UNKNOWN
Classifier: Development Status :: 6 - Mature
Classifier: Intended Audience :: Developers
Classifier: License :: OSI Approved :: MIT License
Classifier: Topic :: Office/Business :: Financial :: Spreadsheet
Classifier: Programming Language :: Python :: 2
Classifier: Programming Language :: Python :: 2.7
Classifier: Programming Language :: Python :: 3
Classifier: Programming Language :: Python :: 3.6
Provides-Extra: test
Provides-Extra: build
